mandate_docs_bulk_uploader/__init__.py
mandate_docs_bulk_uploader-1.0.1.dist-info/METADATA
mandate_docs_bulk_uploader-1.0.1.dist-info/WHEEL
mandate_docs_bulk_uploader-1.0.1.dist-info/entry_points.txt
mandate_docs_bulk_uploader-1.0.1.dist-info/top_level.txt
mandate_docs_bulk_uploader-1.0.1.dist-info/RECORD
